smallerize/__init__.py
smallerize/simulate.py
smallerize/smallerize.py
smallerize/utils.py
smallerize-0.5.0.dist-info/AUTHORS.rst
smallerize-0.5.0.dist-info/LICENSE
smallerize-0.5.0.dist-info/METADATA
smallerize-0.5.0.dist-info/WHEEL
smallerize-0.5.0.dist-info/top_level.txt
smallerize-0.5.0.dist-info/RECORD
