Metadata-Version: 2.1
Name: smallerize
Version: 0.5.0
Summary: A Python implementation of minimisation for clinical trials
Home-page: https://gitlab.com/warsquid/smallerize
Author: Marius Mather
Author-email: marius.mather@gmail.com
License: Mozilla Public License 2.0 (MPL 2.0)
Keywords: smallerize
Platform: UNKNOWN
Classifier: Development Status :: 5 - Production/Stable
Classifier: Intended Audience :: Developers
Classifier: License :: OSI Approved :: Mozilla Public License 2.0 (MPL 2.0)
Classifier: Natural Language :: English
Classifier: Programming Language :: Python :: 3.6
Classifier: Programming Language :: Python :: 3.7
